astrbot_injector/__init__.py
astrbot_injector/injector.py
astrbot_injector/py.typed
astrbot_injector-0.1.2.dist-info/METADATA
astrbot_injector-0.1.2.dist-info/WHEEL
astrbot_injector-0.1.2.dist-info/RECORD
