Metadata-Version: 2.4
Name: astrbot-injector
Version: 0.1.2
Summary: 基于wrapt的依赖注入库.
Project-URL: Homepage, https://github.com/lightjunction/astrbotcanary
Project-URL: Source, https://github.com/lightjunction/astrbotcanary
Author-email: LIghtJUNction <LIghtJUNction.me@gmail.com>
Requires-Python: >=3.13.8
Requires-Dist: wrapt>=1.17.3
